introligo/__init__.py
introligo/__main__.py
introligo/_version.py
introligo/errors.py
introligo/generator.py
introligo/hub.py
introligo/markdown_converter.py
introligo/page_node.py
introligo/utils.py
introligo/yaml_loader.py
introligo/palettes/celin.yaml
introligo/palettes/default.yaml
introligo/templates/conf.py.jinja2
introligo-1.3.0.dist-info/licenses/LICENSE
introligo-1.3.0.dist-info/METADATA
introligo-1.3.0.dist-info/WHEEL
introligo-1.3.0.dist-info/entry_points.txt
introligo-1.3.0.dist-info/top_level.txt
introligo-1.3.0.dist-info/RECORD
