Metadata-Version: 2.4
Name: introligo
Version: 1.3.0
Summary: Professional Sphinx documentation generator with intelligent auto-discovery. Automatically finds and unifies READMEs, changelogs, markdown guides, and API docs into beautifully organized documentation sites.
Home-page: https://github.com/JakubBrzezo/introligo
Author: Jakub Brzezowski
Author-email: Jakub Brzezowski <jakubbrzez@wp.pl>
License:                                  Apache License
Project-URL: Homepage, https://github.com/JakubBrzezo/introligo
Project-URL: Documentation, https://jakubbrzezo.github.io/introligo
Project-URL: Repository, https://github.com/JakubBrzezo/introligo
Project-URL: Bug Tracker, https://github.com/JakubBrzezo/introligo/issues
Project-URL: Changelog, https://github.com/JakubBrzezo/introligo/blob/master/CHANGELOG.md
Keywords: documentation,sphinx,rst,yaml,generator,doxygen,breathe
Classifier: Development Status :: 4 - Beta
Classifier: Intended Audience :: Developers
Classifier: License :: OSI Approved :: Apache Software License
Classifier: Operating System :: OS Independent
Classifier: Programming Language :: Python :: 3
Classifier: Programming Language :: Python :: 3.8
Classifier: Programming Language :: Python :: 3.9
Classifier: Programming Language :: Python :: 3.10
Classifier: Programming Language :: Python :: 3.11
Classifier: Programming Language :: Python :: 3.12
Classifier: Topic :: Documentation
Classifier: Topic :: Software Development :: Documentation
Classifier: Topic :: Text Processing :: Markup :: reStructuredText
Requires-Python: >=3.8
License-File: LICENSE
Requires-Dist: PyYAML>=6.0
Requires-Dist: Jinja2>=3.0
Requires-Dist: sphinx>=4.0
Provides-Extra: docs
Requires-Dist: furo>=2023.3.27; extra == "docs"
Provides-Extra: cpp
Requires-Dist: breathe>=4.0; extra == "cpp"
Provides-Extra: dev
Requires-Dist: pytest>=7.0; extra == "dev"
Requires-Dist: ruff>=0.1.0; extra == "dev"
Requires-Dist: mypy>=1.0; extra == "dev"
Requires-Dist: watchdog>=3.0; extra == "dev"
Dynamic: author
Dynamic: home-page
Dynamic: license-file
Dynamic: requires-python
